LICENSE
README.md
setup.py
Classification/__init__.py
Classification/Attribute/Attribute.c
Classification/Attribute/Attribute.pxd
Classification/Attribute/Attribute.pyx
Classification/Attribute/AttributeType.py
Classification/Attribute/BinaryAttribute.c
Classification/Attribute/BinaryAttribute.pxd
Classification/Attribute/BinaryAttribute.pyx
Classification/Attribute/ContinuousAttribute.c
Classification/Attribute/ContinuousAttribute.pxd
Classification/Attribute/ContinuousAttribute.pyx
Classification/Attribute/DiscreteAttribute.c
Classification/Attribute/DiscreteAttribute.pxd
Classification/Attribute/DiscreteAttribute.pyx
Classification/Attribute/DiscreteIndexedAttribute.c
Classification/Attribute/DiscreteIndexedAttribute.pxd
Classification/Attribute/DiscreteIndexedAttribute.pyx
Classification/Attribute/__init__.py
Classification/DataSet/DataDefinition.c
Classification/DataSet/DataDefinition.pxd
Classification/DataSet/DataDefinition.pyx
Classification/DataSet/DataSet.c
Classification/DataSet/DataSet.pxd
Classification/DataSet/DataSet.pyx
Classification/DataSet/__init__.py
Classification/DistanceMetric/DistanceMetric.c
Classification/DistanceMetric/DistanceMetric.pxd
Classification/DistanceMetric/DistanceMetric.pyx
Classification/DistanceMetric/EuclidianDistance.c
Classification/DistanceMetric/EuclidianDistance.pxd
Classification/DistanceMetric/EuclidianDistance.pyx
Classification/DistanceMetric/MahalanobisDistance.c
Classification/DistanceMetric/MahalanobisDistance.pyx
Classification/DistanceMetric/__init__.py
Classification/Experiment/BootstrapRun.c
Classification/Experiment/BootstrapRun.pyx
Classification/Experiment/Experiment.c
Classification/Experiment/Experiment.pxd
Classification/Experiment/Experiment.pyx
Classification/Experiment/KFoldRun.c
Classification/Experiment/KFoldRun.pxd
Classification/Experiment/KFoldRun.pyx
Classification/Experiment/KFoldRunSeparateTest.c
Classification/Experiment/KFoldRunSeparateTest.pxd
NlpToolkit_Classification_Cy.egg-info/PKG-INFO
NlpToolkit_Classification_Cy.egg-info/SOURCES.txt
NlpToolkit_Classification_Cy.egg-info/dependency_links.txt
NlpToolkit_Classification_Cy.egg-info/requires.txt
NlpToolkit_Classification_Cy.egg-info/top_level.txt
nlptoolkit_classification_cy.egg-info/PKG-INFO
nlptoolkit_classification_cy.egg-info/SOURCES.txt
nlptoolkit_classification_cy.egg-info/dependency_links.txt
nlptoolkit_classification_cy.egg-info/requires.txt
nlptoolkit_classification_cy.egg-info/top_level.txt