Metadata-Version: 2.1
Name: nlptoolkit-classification-cy
Version: 1.0.10
Summary: Classification library
Home-page: https://github.com/StarlangSoftware/Classification-Cy
Author: olcaytaner
Author-email: olcay.yildiz@ozyegin.edu.tr
License: UNKNOWN
Platform: UNKNOWN
